{
  "version": "5",
  "dialect": "mysql",
  "id": "933e4023-a82a-4269-b6b6-6cea4a2edb30",
  "prevId": "75d6d8dd-b188-47c0-80a2-7e1b054c97a0",
  "tables": {
    "audit_findings": {
      "name": "audit_findings",
      "columns": {
        "id": {
          "name": "id",
          "type": "int",
          "primaryKey": false,
          "notNull": true,
          "autoincrement": true
        },
        "auditResultId": {
          "name": "auditResultId",
          "type": "int",
          "primaryKey": false,
          "notNull": true,
          "autoincrement": false
        },
        "severity": {
          "name": "severity",
          "type": "enum('S0','S1','S2','S3')",
          "primaryKey": false,
          "notNull": true,
          "autoincrement": false
        },
        "reasonCode": {
          "name": "reasonCode",
          "type": "enum('MISSING_FIELD','UNREADABLE_FIELD','LOW_CONFIDENCE','INVALID_FORMAT','CONFLICT','OUT_OF_POLICY','INCOMPLETE_EVIDENCE','OCR_FAILURE','PIPELINE_ERROR','SPEC_GAP','SECURITY_RISK')",
          "primaryKey": false,
          "notNull": true,
          "autoincrement": false
        },
        "fieldName": {
          "name": "fieldName",
          "type": "varchar(128)",
          "primaryKey": false,
          "notNull": true,
          "autoincrement": false
        },
        "pageNumber": {
          "name": "pageNumber",
          "type": "int",
          "primaryKey": false,
          "notNull": false,
          "autoincrement": false
        },
        "boundingBox": {
          "name": "boundingBox",
          "type": "json",
          "primaryKey": false,
          "notNull": false,
          "autoincrement": false
        },
        "rawSnippet": {
          "name": "rawSnippet",
          "type": "text",
          "primaryKey": false,
          "notNull": false,
          "autoincrement": false
        },
        "normalisedSnippet": {
          "name": "normalisedSnippet",
          "type": "text",
          "primaryKey": false,
          "notNull": false,
          "autoincrement": false
        },
        "confidence": {
          "name": "confidence",
          "type": "decimal(5,2)",
          "primaryKey": false,
          "notNull": false,
          "autoincrement": false
        },
        "ruleId": {
          "name": "ruleId",
          "type": "varchar(64)",
          "primaryKey": false,
          "notNull": false,
          "autoincrement": false
        },
        "whyItMatters": {
          "name": "whyItMatters",
          "type": "text",
          "primaryKey": false,
          "notNull": false,
          "autoincrement": false
        },
        "suggestedFix": {
          "name": "suggestedFix",
          "type": "text",
          "primaryKey": false,
          "notNull": false,
          "autoincrement": false
        },
        "createdAt": {
          "name": "createdAt",
          "type": "timestamp",
          "primaryKey": false,
          "notNull": true,
          "autoincrement": false,
          "default": "(now())"
        }
      },
      "indexes": {},
      "foreignKeys": {},
      "compositePrimaryKeys": {
        "audit_findings_id": {
          "name": "audit_findings_id",
          "columns": [
            "id"
          ]
        }
      },
      "uniqueConstraints": {},
      "checkConstraint": {}
    },
    "audit_results": {
      "name": "audit_results",
      "columns": {
        "id": {
          "name": "id",
          "type": "int",
          "primaryKey": false,
          "notNull": true,
          "autoincrement": true
        },
        "jobSheetId": {
          "name": "jobSheetId",
          "type": "int",
          "primaryKey": false,
          "notNull": true,
          "autoincrement": false
        },
        "goldSpecId": {
          "name": "goldSpecId",
          "type": "int",
          "primaryKey": false,
          "notNull": true,
          "autoincrement": false
        },
        "runId": {
          "name": "runId",
          "type": "varchar(64)",
          "primaryKey": false,
          "notNull": true,
          "autoincrement": false
        },
        "result": {
          "name": "result",
          "type": "enum('pass','fail','review_queue','waived')",
          "primaryKey": false,
          "notNull": true,
          "autoincrement": false
        },
        "confidenceScore": {
          "name": "confidenceScore",
          "type": "decimal(5,2)",
          "primaryKey": false,
          "notNull": false,
          "autoincrement": false
        },
        "documentStrategy": {
          "name": "documentStrategy",
          "type": "enum('embedded_text','ocr','hybrid')",
          "primaryKey": false,
          "notNull": true,
          "autoincrement": false
        },
        "ocrEngineVersion": {
          "name": "ocrEngineVersion",
          "type": "varchar(32)",
          "primaryKey": false,
          "notNull": false,
          "autoincrement": false
        },
        "pipelineVersion": {
          "name": "pipelineVersion",
          "type": "varchar(32)",
          "primaryKey": false,
          "notNull": true,
          "autoincrement": false
        },
        "reportJson": {
          "name": "reportJson",
          "type": "json",
          "primaryKey": false,
          "notNull": true,
          "autoincrement": false
        },
        "processingTimeMs": {
          "name": "processingTimeMs",
          "type": "int",
          "primaryKey": false,
          "notNull": false,
          "autoincrement": false
        },
        "createdAt": {
          "name": "createdAt",
          "type": "timestamp",
          "primaryKey": false,
          "notNull": true,
          "autoincrement": false,
          "default": "(now())"
        }
      },
      "indexes": {},
      "foreignKeys": {},
      "compositePrimaryKeys": {
        "audit_results_id": {
          "name": "audit_results_id",
          "columns": [
            "id"
          ]
        }
      },
      "uniqueConstraints": {},
      "checkConstraint": {}
    },
    "disputes": {
      "name": "disputes",
      "columns": {
        "id": {
          "name": "id",
          "type": "int",
          "primaryKey": false,
          "notNull": true,
          "autoincrement": true
        },
        "auditFindingId": {
          "name": "auditFindingId",
          "type": "int",
          "primaryKey": false,
          "notNull": true,
          "autoincrement": false
        },
        "raisedBy": {
          "name": "raisedBy",
          "type": "int",
          "primaryKey": false,
          "notNull": true,
          "autoincrement": false
        },
        "status": {
          "name": "status",
          "type": "enum('open','under_review','accepted','rejected','escalated')",
          "primaryKey": false,
          "notNull": true,
          "autoincrement": false,
          "default": "'open'"
        },
        "reason": {
          "name": "reason",
          "type": "text",
          "primaryKey": false,
          "notNull": true,
          "autoincrement": false
        },
        "evidenceUrls": {
          "name": "evidenceUrls",
          "type": "json",
          "primaryKey": false,
          "notNull": false,
          "autoincrement": false
        },
        "reviewerId": {
          "name": "reviewerId",
          "type": "int",
          "primaryKey": false,
          "notNull": false,
          "autoincrement": false
        },
        "reviewNotes": {
          "name": "reviewNotes",
          "type": "text",
          "primaryKey": false,
          "notNull": false,
          "autoincrement": false
        },
        "resolvedAt": {
          "name": "resolvedAt",
          "type": "timestamp",
          "primaryKey": false,
          "notNull": false,
          "autoincrement": false
        },
        "createdAt": {
          "name": "createdAt",
          "type": "timestamp",
          "primaryKey": false,
          "notNull": true,
          "autoincrement": false,
          "default": "(now())"
        },
        "updatedAt": {
          "name": "updatedAt",
          "type": "timestamp",
          "primaryKey": false,
          "notNull": true,
          "autoincrement": false,
          "onUpdate": true,
          "default": "(now())"
        }
      },
      "indexes": {},
      "foreignKeys": {},
      "compositePrimaryKeys": {
        "disputes_id": {
          "name": "disputes_id",
          "columns": [
            "id"
          ]
        }
      },
      "uniqueConstraints": {},
      "checkConstraint": {}
    },
    "gold_specs": {
      "name": "gold_specs",
      "columns": {
        "id": {
          "name": "id",
          "type": "int",
          "primaryKey": false,
          "notNull": true,
          "autoincrement": true
        },
        "name": {
          "name": "name",
          "type": "varchar(255)",
          "primaryKey": false,
          "notNull": true,
          "autoincrement": false
        },
        "version": {
          "name": "version",
          "type": "varchar(32)",
          "primaryKey": false,
          "notNull": true,
          "autoincrement": false
        },
        "description": {
          "name": "description",
          "type": "text",
          "primaryKey": false,
          "notNull": false,
          "autoincrement": false
        },
        "schema": {
          "name": "schema",
          "type": "json",
          "primaryKey": false,
          "notNull": true,
          "autoincrement": false
        },
        "specType": {
          "name": "specType",
          "type": "enum('base','client','contract','workType')",
          "primaryKey": false,
          "notNull": true,
          "autoincrement": false,
          "default": "'base'"
        },
        "parentSpecId": {
          "name": "parentSpecId",
          "type": "int",
          "primaryKey": false,
          "notNull": false,
          "autoincrement": false
        },
        "isActive": {
          "name": "isActive",
          "type": "boolean",
          "primaryKey": false,
          "notNull": true,
          "autoincrement": false,
          "default": true
        },
        "createdBy": {
          "name": "createdBy",
          "type": "int",
          "primaryKey": false,
          "notNull": true,
          "autoincrement": false
        },
        "createdAt": {
          "name": "createdAt",
          "type": "timestamp",
          "primaryKey": false,
          "notNull": true,
          "autoincrement": false,
          "default": "(now())"
        },
        "updatedAt": {
          "name": "updatedAt",
          "type": "timestamp",
          "primaryKey": false,
          "notNull": true,
          "autoincrement": false,
          "onUpdate": true,
          "default": "(now())"
        }
      },
      "indexes": {},
      "foreignKeys": {},
      "compositePrimaryKeys": {
        "gold_specs_id": {
          "name": "gold_specs_id",
          "columns": [
            "id"
          ]
        }
      },
      "uniqueConstraints": {},
      "checkConstraint": {}
    },
    "job_sheets": {
      "name": "job_sheets",
      "columns": {
        "id": {
          "name": "id",
          "type": "int",
          "primaryKey": false,
          "notNull": true,
          "autoincrement": true
        },
        "referenceNumber": {
          "name": "referenceNumber",
          "type": "varchar(64)",
          "primaryKey": false,
          "notNull": false,
          "autoincrement": false
        },
        "fileUrl": {
          "name": "fileUrl",
          "type": "varchar(512)",
          "primaryKey": false,
          "notNull": true,
          "autoincrement": false
        },
        "fileKey": {
          "name": "fileKey",
          "type": "varchar(256)",
          "primaryKey": false,
          "notNull": true,
          "autoincrement": false
        },
        "fileName": {
          "name": "fileName",
          "type": "varchar(255)",
          "primaryKey": false,
          "notNull": true,
          "autoincrement": false
        },
        "fileType": {
          "name": "fileType",
          "type": "varchar(64)",
          "primaryKey": false,
          "notNull": true,
          "autoincrement": false
        },
        "fileSizeBytes": {
          "name": "fileSizeBytes",
          "type": "int",
          "primaryKey": false,
          "notNull": false,
          "autoincrement": false
        },
        "fileHash": {
          "name": "fileHash",
          "type": "varchar(64)",
          "primaryKey": false,
          "notNull": false,
          "autoincrement": false
        },
        "status": {
          "name": "status",
          "type": "enum('pending','processing','completed','failed','review_queue')",
          "primaryKey": false,
          "notNull": true,
          "autoincrement": false,
          "default": "'pending'"
        },
        "technicianId": {
          "name": "technicianId",
          "type": "int",
          "primaryKey": false,
          "notNull": false,
          "autoincrement": false
        },
        "siteInfo": {
          "name": "siteInfo",
          "type": "text",
          "primaryKey": false,
          "notNull": false,
          "autoincrement": false
        },
        "uploadedBy": {
          "name": "uploadedBy",
          "type": "int",
          "primaryKey": false,
          "notNull": true,
          "autoincrement": false
        },
        "createdAt": {
          "name": "createdAt",
          "type": "timestamp",
          "primaryKey": false,
          "notNull": true,
          "autoincrement": false,
          "default": "(now())"
        },
        "updatedAt": {
          "name": "updatedAt",
          "type": "timestamp",
          "primaryKey": false,
          "notNull": true,
          "autoincrement": false,
          "onUpdate": true,
          "default": "(now())"
        }
      },
      "indexes": {},
      "foreignKeys": {},
      "compositePrimaryKeys": {
        "job_sheets_id": {
          "name": "job_sheets_id",
          "columns": [
            "id"
          ]
        }
      },
      "uniqueConstraints": {},
      "checkConstraint": {}
    },
    "processing_settings": {
      "name": "processing_settings",
      "columns": {
        "id": {
          "name": "id",
          "type": "int",
          "primaryKey": false,
          "notNull": true,
          "autoincrement": true
        },
        "settingKey": {
          "name": "settingKey",
          "type": "varchar(64)",
          "primaryKey": false,
          "notNull": true,
          "autoincrement": false
        },
        "settingValue": {
          "name": "settingValue",
          "type": "json",
          "primaryKey": false,
          "notNull": true,
          "autoincrement": false
        },
        "description": {
          "name": "description",
          "type": "text",
          "primaryKey": false,
          "notNull": false,
          "autoincrement": false
        },
        "category": {
          "name": "category",
          "type": "enum('extraction','validation','performance','notifications')",
          "primaryKey": false,
          "notNull": true,
          "autoincrement": false,
          "default": "'extraction'"
        },
        "updatedBy": {
          "name": "updatedBy",
          "type": "int",
          "primaryKey": false,
          "notNull": false,
          "autoincrement": false
        },
        "createdAt": {
          "name": "createdAt",
          "type": "timestamp",
          "primaryKey": false,
          "notNull": true,
          "autoincrement": false,
          "default": "(now())"
        },
        "updatedAt": {
          "name": "updatedAt",
          "type": "timestamp",
          "primaryKey": false,
          "notNull": true,
          "autoincrement": false,
          "onUpdate": true,
          "default": "(now())"
        }
      },
      "indexes": {},
      "foreignKeys": {},
      "compositePrimaryKeys": {
        "processing_settings_id": {
          "name": "processing_settings_id",
          "columns": [
            "id"
          ]
        }
      },
      "uniqueConstraints": {
        "processing_settings_settingKey_unique": {
          "name": "processing_settings_settingKey_unique",
          "columns": [
            "settingKey"
          ]
        }
      },
      "checkConstraint": {}
    },
    "selection_traces": {
      "name": "selection_traces",
      "columns": {
        "id": {
          "name": "id",
          "type": "int",
          "primaryKey": false,
          "notNull": true,
          "autoincrement": true
        },
        "jobSheetId": {
          "name": "jobSheetId",
          "type": "int",
          "primaryKey": false,
          "notNull": true,
          "autoincrement": false
        },
        "templateId": {
          "name": "templateId",
          "type": "int",
          "primaryKey": false,
          "notNull": false,
          "autoincrement": false
        },
        "versionId": {
          "name": "versionId",
          "type": "int",
          "primaryKey": false,
          "notNull": false,
          "autoincrement": false
        },
        "confidenceBand": {
          "name": "confidenceBand",
          "type": "enum('HIGH','MEDIUM','LOW')",
          "primaryKey": false,
          "notNull": true,
          "autoincrement": false
        },
        "topScore": {
          "name": "topScore",
          "type": "decimal(5,2)",
          "primaryKey": false,
          "notNull": true,
          "autoincrement": false
        },
        "runnerUpScore": {
          "name": "runnerUpScore",
          "type": "decimal(5,2)",
          "primaryKey": false,
          "notNull": false,
          "autoincrement": false
        },
        "scoreGap": {
          "name": "scoreGap",
          "type": "decimal(5,2)",
          "primaryKey": false,
          "notNull": false,
          "autoincrement": false
        },
        "scoresJson": {
          "name": "scoresJson",
          "type": "json",
          "primaryKey": false,
          "notNull": true,
          "autoincrement": false
        },
        "tokensJson": {
          "name": "tokensJson",
          "type": "json",
          "primaryKey": false,
          "notNull": true,
          "autoincrement": false
        },
        "autoProcessingAllowed": {
          "name": "autoProcessingAllowed",
          "type": "boolean",
          "primaryKey": false,
          "notNull": true,
          "autoincrement": false,
          "default": false
        },
        "blockReason": {
          "name": "blockReason",
          "type": "varchar(255)",
          "primaryKey": false,
          "notNull": false,
          "autoincrement": false
        },
        "createdAt": {
          "name": "createdAt",
          "type": "timestamp",
          "primaryKey": false,
          "notNull": true,
          "autoincrement": false,
          "default": "(now())"
        }
      },
      "indexes": {},
      "foreignKeys": {},
      "compositePrimaryKeys": {
        "selection_traces_id": {
          "name": "selection_traces_id",
          "columns": [
            "id"
          ]
        }
      },
      "uniqueConstraints": {},
      "checkConstraint": {}
    },
    "system_audit_log": {
      "name": "system_audit_log",
      "columns": {
        "id": {
          "name": "id",
          "type": "int",
          "primaryKey": false,
          "notNull": true,
          "autoincrement": true
        },
        "userId": {
          "name": "userId",
          "type": "int",
          "primaryKey": false,
          "notNull": false,
          "autoincrement": false
        },
        "action": {
          "name": "action",
          "type": "varchar(64)",
          "primaryKey": false,
          "notNull": true,
          "autoincrement": false
        },
        "entityType": {
          "name": "entityType",
          "type": "varchar(64)",
          "primaryKey": false,
          "notNull": true,
          "autoincrement": false
        },
        "entityId": {
          "name": "entityId",
          "type": "int",
          "primaryKey": false,
          "notNull": false,
          "autoincrement": false
        },
        "details": {
          "name": "details",
          "type": "json",
          "primaryKey": false,
          "notNull": false,
          "autoincrement": false
        },
        "ipAddress": {
          "name": "ipAddress",
          "type": "varchar(45)",
          "primaryKey": false,
          "notNull": false,
          "autoincrement": false
        },
        "userAgent": {
          "name": "userAgent",
          "type": "text",
          "primaryKey": false,
          "notNull": false,
          "autoincrement": false
        },
        "createdAt": {
          "name": "createdAt",
          "type": "timestamp",
          "primaryKey": false,
          "notNull": true,
          "autoincrement": false,
          "default": "(now())"
        }
      },
      "indexes": {},
      "foreignKeys": {},
      "compositePrimaryKeys": {
        "system_audit_log_id": {
          "name": "system_audit_log_id",
          "columns": [
            "id"
          ]
        }
      },
      "uniqueConstraints": {},
      "checkConstraint": {}
    },
    "template_versions": {
      "name": "template_versions",
      "columns": {
        "id": {
          "name": "id",
          "type": "int",
          "primaryKey": false,
          "notNull": true,
          "autoincrement": true
        },
        "templateId": {
          "name": "templateId",
          "type": "int",
          "primaryKey": false,
          "notNull": true,
          "autoincrement": false
        },
        "version": {
          "name": "version",
          "type": "varchar(32)",
          "primaryKey": false,
          "notNull": true,
          "autoincrement": false
        },
        "hashSha256": {
          "name": "hashSha256",
          "type": "varchar(64)",
          "primaryKey": false,
          "notNull": true,
          "autoincrement": false
        },
        "specJson": {
          "name": "specJson",
          "type": "json",
          "primaryKey": false,
          "notNull": true,
          "autoincrement": false
        },
        "selectionConfigJson": {
          "name": "selectionConfigJson",
          "type": "json",
          "primaryKey": false,
          "notNull": true,
          "autoincrement": false
        },
        "roiJson": {
          "name": "roiJson",
          "type": "json",
          "primaryKey": false,
          "notNull": false,
          "autoincrement": false
        },
        "isActive": {
          "name": "isActive",
          "type": "boolean",
          "primaryKey": false,
          "notNull": true,
          "autoincrement": false,
          "default": false
        },
        "changeNotes": {
          "name": "changeNotes",
          "type": "text",
          "primaryKey": false,
          "notNull": false,
          "autoincrement": false
        },
        "createdBy": {
          "name": "createdBy",
          "type": "int",
          "primaryKey": false,
          "notNull": true,
          "autoincrement": false
        },
        "createdAt": {
          "name": "createdAt",
          "type": "timestamp",
          "primaryKey": false,
          "notNull": true,
          "autoincrement": false,
          "default": "(now())"
        }
      },
      "indexes": {},
      "foreignKeys": {},
      "compositePrimaryKeys": {
        "template_versions_id": {
          "name": "template_versions_id",
          "columns": [
            "id"
          ]
        }
      },
      "uniqueConstraints": {},
      "checkConstraint": {}
    },
    "templates": {
      "name": "templates",
      "columns": {
        "id": {
          "name": "id",
          "type": "int",
          "primaryKey": false,
          "notNull": true,
          "autoincrement": true
        },
        "templateId": {
          "name": "templateId",
          "type": "varchar(128)",
          "primaryKey": false,
          "notNull": true,
          "autoincrement": false
        },
        "name": {
          "name": "name",
          "type": "varchar(255)",
          "primaryKey": false,
          "notNull": true,
          "autoincrement": false
        },
        "client": {
          "name": "client",
          "type": "varchar(128)",
          "primaryKey": false,
          "notNull": false,
          "autoincrement": false
        },
        "assetType": {
          "name": "assetType",
          "type": "varchar(128)",
          "primaryKey": false,
          "notNull": false,
          "autoincrement": false
        },
        "workType": {
          "name": "workType",
          "type": "varchar(128)",
          "primaryKey": false,
          "notNull": false,
          "autoincrement": false
        },
        "status": {
          "name": "status",
          "type": "enum('draft','active','deprecated','archived')",
          "primaryKey": false,
          "notNull": true,
          "autoincrement": false,
          "default": "'draft'"
        },
        "description": {
          "name": "description",
          "type": "text",
          "primaryKey": false,
          "notNull": false,
          "autoincrement": false
        },
        "createdBy": {
          "name": "createdBy",
          "type": "int",
          "primaryKey": false,
          "notNull": true,
          "autoincrement": false
        },
        "createdAt": {
          "name": "createdAt",
          "type": "timestamp",
          "primaryKey": false,
          "notNull": true,
          "autoincrement": false,
          "default": "(now())"
        },
        "updatedAt": {
          "name": "updatedAt",
          "type": "timestamp",
          "primaryKey": false,
          "notNull": true,
          "autoincrement": false,
          "onUpdate": true,
          "default": "(now())"
        }
      },
      "indexes": {},
      "foreignKeys": {},
      "compositePrimaryKeys": {
        "templates_id": {
          "name": "templates_id",
          "columns": [
            "id"
          ]
        }
      },
      "uniqueConstraints": {
        "templates_templateId_unique": {
          "name": "templates_templateId_unique",
          "columns": [
            "templateId"
          ]
        }
      },
      "checkConstraint": {}
    },
    "users": {
      "name": "users",
      "columns": {
        "id": {
          "name": "id",
          "type": "int",
          "primaryKey": false,
          "notNull": true,
          "autoincrement": true
        },
        "openId": {
          "name": "openId",
          "type": "varchar(64)",
          "primaryKey": false,
          "notNull": true,
          "autoincrement": false
        },
        "name": {
          "name": "name",
          "type": "text",
          "primaryKey": false,
          "notNull": false,
          "autoincrement": false
        },
        "email": {
          "name": "email",
          "type": "varchar(320)",
          "primaryKey": false,
          "notNull": false,
          "autoincrement": false
        },
        "loginMethod": {
          "name": "loginMethod",
          "type": "varchar(64)",
          "primaryKey": false,
          "notNull": false,
          "autoincrement": false
        },
        "role": {
          "name": "role",
          "type": "enum('user','admin','qa_lead','technician')",
          "primaryKey": false,
          "notNull": true,
          "autoincrement": false,
          "default": "'user'"
        },
        "createdAt": {
          "name": "createdAt",
          "type": "timestamp",
          "primaryKey": false,
          "notNull": true,
          "autoincrement": false,
          "default": "(now())"
        },
        "updatedAt": {
          "name": "updatedAt",
          "type": "timestamp",
          "primaryKey": false,
          "notNull": true,
          "autoincrement": false,
          "onUpdate": true,
          "default": "(now())"
        },
        "lastSignedIn": {
          "name": "lastSignedIn",
          "type": "timestamp",
          "primaryKey": false,
          "notNull": true,
          "autoincrement": false,
          "default": "(now())"
        }
      },
      "indexes": {},
      "foreignKeys": {},
      "compositePrimaryKeys": {
        "users_id": {
          "name": "users_id",
          "columns": [
            "id"
          ]
        }
      },
      "uniqueConstraints": {
        "users_openId_unique": {
          "name": "users_openId_unique",
          "columns": [
            "openId"
          ]
        }
      },
      "checkConstraint": {}
    },
    "waivers": {
      "name": "waivers",
      "columns": {
        "id": {
          "name": "id",
          "type": "int",
          "primaryKey": false,
          "notNull": true,
          "autoincrement": true
        },
        "auditFindingId": {
          "name": "auditFindingId",
          "type": "int",
          "primaryKey": false,
          "notNull": true,
          "autoincrement": false
        },
        "approverId": {
          "name": "approverId",
          "type": "int",
          "primaryKey": false,
          "notNull": true,
          "autoincrement": false
        },
        "reason": {
          "name": "reason",
          "type": "text",
          "primaryKey": false,
          "notNull": true,
          "autoincrement": false
        },
        "expiresAt": {
          "name": "expiresAt",
          "type": "timestamp",
          "primaryKey": false,
          "notNull": false,
          "autoincrement": false
        },
        "auditTrail": {
          "name": "auditTrail",
          "type": "json",
          "primaryKey": false,
          "notNull": true,
          "autoincrement": false
        },
        "createdAt": {
          "name": "createdAt",
          "type": "timestamp",
          "primaryKey": false,
          "notNull": true,
          "autoincrement": false,
          "default": "(now())"
        }
      },
      "indexes": {},
      "foreignKeys": {},
      "compositePrimaryKeys": {
        "waivers_id": {
          "name": "waivers_id",
          "columns": [
            "id"
          ]
        }
      },
      "uniqueConstraints": {},
      "checkConstraint": {}
    }
  },
  "views": {},
  "_meta": {
    "schemas": {},
    "tables": {},
    "columns": {}
  },
  "internal": {
    "tables": {},
    "indexes": {}
  }
}